dauntlessdb.py
dauntlessdb-0.1.0.dist-info/METADATA
dauntlessdb-0.1.0.dist-info/WHEEL
dauntlessdb-0.1.0.dist-info/RECORD
