Metadata-Version: 2.1
Name: dauntlessdb
Version: 0.1.0
Summary: 
Author: gssakash
Author-email: gsaisriram.akash@gmail.com
Requires-Python: >=3.12,<4.0
Classifier: Programming Language :: Python :: 3
Classifier: Programming Language :: Python :: 3.12
Classifier: Programming Language :: Python :: 3.13
Requires-Dist: numpy (>=2.2.0,<3.0.0)
Requires-Dist: pytest (>=8.3.4,<9.0.0)
